aws_databridge/__init__.py
aws_databridge/main.py
aws_databridge/db_import/__init__.py
aws_databridge/db_import/document.py
aws_databridge/db_import/dynamodb.py
aws_databridge/db_import/neptune.py
aws_databridge/db_import/rds.py
aws_databridge/utils/__init__.py
aws_databridge/utils/convert_to.py
aws_databridge/utils/sanitize.py
aws_databridge-2.0.3.dist-info/METADATA
aws_databridge-2.0.3.dist-info/WHEEL
aws_databridge-2.0.3.dist-info/entry_points.txt
aws_databridge-2.0.3.dist-info/top_level.txt
aws_databridge-2.0.3.dist-info/RECORD
