Metadata-Version: 2.1
Name: aws-databridge
Version: 2.0.3
Summary: An AWS EC2 CLI application that supports XML, TXT, JSON, and CSV imports to various AWS databases.
Home-page: https://github.com/Jaysalgado/aws-databridge
Author: Jay, Aban, Matt
Classifier: Programming Language :: Python :: 3
Classifier: License :: OSI Approved :: MIT License
Classifier: Operating System :: OS Independent
Requires-Python: >=3.6
Requires-Dist: boto3 >=1.20.0
Requires-Dist: pandas
Requires-Dist: pymysql
Requires-Dist: lxml
Requires-Dist: requests
Requires-Dist: pymongo
